odoo10_addon_l10n_it_withholding_tax_payment_order-10.0.1.0.0.99.dev3-py3.8-nspkg.pth
odoo/addons/l10n_it_withholding_tax_payment_order/README.rst
odoo/addons/l10n_it_withholding_tax_payment_order/__init__.py
odoo/addons/l10n_it_withholding_tax_payment_order/__manifest__.py
odoo/addons/l10n_it_withholding_tax_payment_order/i18n/l10n_it_withholding_tax_payment_order.pot
odoo/addons/l10n_it_withholding_tax_payment_order/models/__init__.py
odoo/addons/l10n_it_withholding_tax_payment_order/models/account_move_line.py
odoo/addons/l10n_it_withholding_tax_payment_order/readme/CONTRIBUTORS.rst
odoo/addons/l10n_it_withholding_tax_payment_order/readme/DESCRIPTION.rst
odoo/addons/l10n_it_withholding_tax_payment_order/static/description/icon.png
odoo/addons/l10n_it_withholding_tax_payment_order/static/description/index.html
odoo/addons/l10n_it_withholding_tax_payment_order/tests/__init__.py
odoo/addons/l10n_it_withholding_tax_payment_order/tests/test_l10n_it_withholding_tax_payment_order.py
odoo10_addon_l10n_it_withholding_tax_payment_order-10.0.1.0.0.99.dev3.dist-info/METADATA
odoo10_addon_l10n_it_withholding_tax_payment_order-10.0.1.0.0.99.dev3.dist-info/WHEEL
odoo10_addon_l10n_it_withholding_tax_payment_order-10.0.1.0.0.99.dev3.dist-info/namespace_packages.txt
odoo10_addon_l10n_it_withholding_tax_payment_order-10.0.1.0.0.99.dev3.dist-info/top_level.txt
odoo10_addon_l10n_it_withholding_tax_payment_order-10.0.1.0.0.99.dev3.dist-info/RECORD
