Metadata-Version: 2.1
Name: odoo10-addon-l10n-it-withholding-tax-payment-order
Version: 10.0.1.0.0.99.dev3
Summary: Modulo ponte tra ritenuta d'acconto e ordine di pagamento
Home-page: https://github.com/OCA/l10n-italy/tree/10.0/l10n_it_withholding_tax_payment_order
Author: Agile Business Group, Odoo Community Association (OCA)
Author-email: support@odoo-community.org
License: AGPL-3
Platform: UNKNOWN
Classifier: Programming Language :: Python
Classifier: Framework :: Odoo
Classifier: Framework :: Odoo :: 10.0
Classifier: License :: OSI Approved :: GNU Affero General Public License v3
Requires-Python: ~=2.7
Requires-Dist: odoo10-addon-account-payment-order
Requires-Dist: odoo10-addon-l10n-it-withholding-tax
Requires-Dist: odoo <10.1dev,>=10.0
